{
  "sections": {
    "main": {
      "type": "main-page",
      "disabled": true,
      "settings": {
        "page_title": false,
        "section_width": 100
      }
    },
    "16417150465b421498": {
      "type": "image-banner",
      "blocks": {
        "1641715046f3b6ca1f-0": {
          "type": "heading",
          "disabled": true,
          "settings": {
            "heading": "Image banner",
            "heading_size": "medium"
          }
        },
        "1641715046f3b6ca1f-1": {
          "type": "text",
          "disabled": true,
          "settings": {
            "text": "Give customers details about the banner image(s) or content on the template."
          }
        },
        "1641715046f3b6ca1f-2": {
          "type": "buttons",
          "disabled": true,
          "settings": {
            "button_label_1": "Button label",
            "button_link_1": "",
            "button_style_secondary_1": false,
            "button_label_2": "Button label",
            "button_link_2": "",
            "button_style_secondary_2": false
          }
        }
      },
      "block_order": [
        "1641715046f3b6ca1f-0",
        "1641715046f3b6ca1f-1",
        "1641715046f3b6ca1f-2"
      ],
      "settings": {
        "image_2": "shopify:\/\/shop_images\/Mask_Group_b98a52fb-33c4-4a94-959c-281201f193e8.png",
        "mobile_image": "shopify:\/\/shop_images\/retail.jpg",
        "sec_class": "",
        "image_height": "large",
        "adapt_height_first_image": false,
        "desktop_text_box_position": "center",
        "show_text_box": false,
        "image_overlay_opacity": 0,
        "color_scheme": "background-1",
        "stack_images_on_mobile": true,
        "show_text_below": true
      }
    },
    "storeCode": {
      "type": "store-details",
      "settings": {
        "title": "Locations",
        "subtitle": "Please add your postcode to find a store.",
        "filter_title": "Filter by services:",
        "search_title": "Search:",
        "group_title": "Filter by region:",
        "find_me_title": "Use current location",
        "contact_title": "Contact information:",
        "hours_title": "Shop hours:",
        "no_stores_found_text": "No stores found matching your selected filters.",
        "marker_icon_title": "location-pin",
        "cluster_icon_title": "location-pin",
        "user_icon_title": "user-location",
        "search_icon_title": "search-location"
      }
    }
  },
  "order": [
    "main",
    "16417150465b421498",
    "storeCode"
  ]
}
